preconvert_numpy/__init__.py
preconvert_numpy/converters.py
preconvert_numpy-0.0.3.dist-info/entry_points.txt
preconvert_numpy-0.0.3.dist-info/WHEEL
preconvert_numpy-0.0.3.dist-info/METADATA
preconvert_numpy-0.0.3.dist-info/RECORD
